LICENSE
MANIFEST.in
README.rst
aiosc.py
setup.py
aiosc.egg-info/PKG-INFO
aiosc.egg-info/SOURCES.txt
aiosc.egg-info/dependency_links.txt
aiosc.egg-info/top_level.txt
examples/echo_server.py
examples/hello.py