Metadata-Version: 2.1
Name: aiosc
Version: 0.2
Summary: Minimalistic Open Sound Control (OSC) communication module using asyncio
Home-page: https://github.com/artfwo/aiosc
Author: Artem Popov
Author-email: artfwo@gmail.com
License: MIT
Classifier: Development Status :: 4 - Beta
Classifier: Intended Audience :: Developers
Classifier: License :: OSI Approved :: MIT License
Classifier: Programming Language :: Python :: 3
Classifier: Topic :: Multimedia :: Sound/Audio
Classifier: Topic :: Software Development :: Libraries
Classifier: Topic :: System :: Networking
License-File: LICENSE
